django_pg_hll/__init__.py
django_pg_hll/aggregate.py
django_pg_hll/bulk_update.py
django_pg_hll/compatibility.py
django_pg_hll/fields.py
django_pg_hll/migration.py
django_pg_hll/transforms.py
django_pg_hll/utils.py
django_pg_hll/values.py
django_pg_hll-2.2.0.dist-info/licenses/LICENSE
django_pg_hll-2.2.0.dist-info/METADATA
django_pg_hll-2.2.0.dist-info/WHEEL
django_pg_hll-2.2.0.dist-info/top_level.txt
django_pg_hll-2.2.0.dist-info/RECORD
