Metadata-Version: 2.4
Name: django-pg-hll
Version: 2.2.0
Summary: Provides a django wrapper for postgresql-hll library by CitusData
Home-page: https://github.com/M1ha-Shvn/django-pg-hll
Author: Mikhail Shvein
Author-email: work_shvein_mihail@mail.ru
License: BSD 3-clause "New" or "Revised" License
License-File: LICENSE
Requires-Dist: Django>=1.7
Requires-Dist: typing; python_version < "3.5"
Dynamic: author
Dynamic: author-email
Dynamic: description
Dynamic: description-content-type
Dynamic: home-page
Dynamic: license
Dynamic: license-file
Dynamic: requires-dist
Dynamic: summary
